{
  "date": "2026-07-21",
  "scrapedAt": "2026-07-21T15:23:43.143Z",
  "companies": [
    {
      "symbol": "DSE",
      "name": "Dar es Salaam Stock Exchange Plc",
      "price": 6710,
      "open": 6850,
      "prevClose": 6710,
      "high": 6880,
      "low": 6540,
      "change": 0,
      "turnover": 11707700,
      "volume": 873,
      "deals": 23,
      "marketCap": 16789,
      "pe": null,
      "eps": null,
      "dividendYield": null,
      "dividendPerShare": null,
      "bookValue": null,
      "pb": null,
      "sharesOutstanding": null
    },
    {
      "symbol": "CRDB",
      "name": "CRDB Bank Plc",
      "price": 2680,
      "open": 2680,
      "prevClose": 2680,
      "high": 2710,
      "low": 2650,
      "change": 0,
      "turnover": 836130220,
      "volume": 90959,
      "deals": 1288,
      "marketCap": 76474,
      "pe": null,
      "eps": null,
      "dividendYield": null,
      "dividendPerShare": null,
      "bookValue": null,
      "pb": null,
      "sharesOutstanding": null
    },
    {
      "symbol": "DCB",
      "name": "DCB Commercial Bank Plc",
      "price": 475,
      "open": 475,
      "prevClose": 475,
      "high": 495,
      "low": 450,
      "change": 0,
      "turnover": 24335755,
      "volume": 7932,
      "deals": 107,
      "marketCap": 16075,
      "pe": null,
      "eps": null,
      "dividendYield": null,
      "dividendPerShare": null,
      "bookValue": null,
      "pb": null,
      "sharesOutstanding": null
    },
    {
      "symbol": "EABL",
      "name": "East African Breweries Ltd",
      "price": 5420,
      "open": 5510,
      "prevClose": 0,
      "high": 0,
      "low": 0,
      "change": 0,
      "turnover": 0,
      "volume": 65,
      "deals": 0,
      "marketCap": 0,
      "pe": null,
      "eps": null,
      "dividendYield": null,
      "dividendPerShare": null,
      "bookValue": null,
      "pb": null,
      "sharesOutstanding": null
    },
    {
      "symbol": "JHL",
      "name": "Jubilee Holdings Ltd",
      "price": 8650,
      "open": 8650,
      "prevClose": 0,
      "high": 0,
      "low": 0,
      "change": 0,
      "turnover": 0,
      "volume": 12,
      "deals": 0,
      "marketCap": 0,
      "pe": null,
      "eps": null,
      "dividendYield": null,
      "dividendPerShare": null,
      "bookValue": null,
      "pb": null,
      "sharesOutstanding": null
    },
    {
      "symbol": "KA",
      "name": "Kenya Airways Ltd",
      "price": 115,
      "open": 115,
      "prevClose": 0,
      "high": 0,
      "low": 0,
      "change": 0,
      "turnover": 0,
      "volume": 311,
      "deals": 0,
      "marketCap": 0,
      "pe": null,
      "eps": null,
      "dividendYield": null,
      "dividendPerShare": null,
      "bookValue": null,
      "pb": null,
      "sharesOutstanding": null
    },
    {
      "symbol": "KCB",
      "name": "KCB Group Plc",
      "price": 1930,
      "open": 1930,
      "prevClose": 1930,
      "high": 1930,
      "low": 1920,
      "change": 0,
      "turnover": 10829460,
      "volume": 1382,
      "deals": 38,
      "marketCap": 23803,
      "pe": null,
      "eps": null,
      "dividendYield": null,
      "dividendPerShare": null,
      "bookValue": null,
      "pb": null,
      "sharesOutstanding": null
    },
    {
      "symbol": "MBP",
      "name": "Mkombozi Commercial Bank Plc",
      "price": 1850,
      "open": 1740,
      "prevClose": 1850,
      "high": 1910,
      "low": 1800,
      "change": 6.32,
      "turnover": 3849760,
      "volume": 656,
      "deals": 31,
      "marketCap": 3970,
      "pe": null,
      "eps": null,
      "dividendYield": null,
      "dividendPerShare": null,
      "bookValue": null,
      "pb": null,
      "sharesOutstanding": null
    },
    {
      "symbol": "NICO",
      "name": "NICOL Insurance Co Ltd",
      "price": 3830,
      "open": 3740,
      "prevClose": 3830,
      "high": 3850,
      "low": 3800,
      "change": 2.41,
      "turnover": 30663610,
      "volume": 8256,
      "deals": 68,
      "marketCap": 10693,
      "pe": null,
      "eps": null,
      "dividendYield": null,
      "dividendPerShare": null,
      "bookValue": null,
      "pb": null,
      "sharesOutstanding": null
    },
    {
      "symbol": "NMB",
      "name": "NMB Bank Plc",
      "price": 16750,
      "open": 16750,
      "prevClose": 16750,
      "high": 16770,
      "low": 16730,
      "change": 0,
      "turnover": 656865120,
      "volume": 5608,
      "deals": 195,
      "marketCap": 6918,
      "pe": null,
      "eps": null,
      "dividendYield": null,
      "dividendPerShare": null,
      "bookValue": null,
      "pb": null,
      "sharesOutstanding": null
    },
    {
      "symbol": "NMG",
      "name": "Nation Media Group Ltd",
      "price": 260,
      "open": 250,
      "prevClose": 0,
      "high": 0,
      "low": 0,
      "change": 4,
      "turnover": 0,
      "volume": 309,
      "deals": 0,
      "marketCap": 193,
      "pe": null,
      "eps": null,
      "dividendYield": null,
      "dividendPerShare": null,
      "bookValue": null,
      "pb": null,
      "sharesOutstanding": null
    },
    {
      "symbol": "PAL",
      "name": "Precision Air Services Plc",
      "price": 380,
      "open": 415,
      "prevClose": 380,
      "high": 390,
      "low": 355,
      "change": 0,
      "turnover": 735770,
      "volume": 4820,
      "deals": 39,
      "marketCap": 19109,
      "pe": null,
      "eps": null,
      "dividendYield": null,
      "dividendPerShare": null,
      "bookValue": null,
      "pb": null,
      "sharesOutstanding": null
    },
    {
      "symbol": "SWIS",
      "name": "Swissport Tanzania Plc",
      "price": 2320,
      "open": 2450,
      "prevClose": 2320,
      "high": 2600,
      "low": 2240,
      "change": 0,
      "turnover": 21292220,
      "volume": 19453,
      "deals": 60,
      "marketCap": 6861,
      "pe": null,
      "eps": null,
      "dividendYield": null,
      "dividendPerShare": null,
      "bookValue": null,
      "pb": null,
      "sharesOutstanding": null
    },
    {
      "symbol": "TBL",
      "name": "Tanzania Breweries Ltd",
      "price": 9800,
      "open": 9830,
      "prevClose": 9800,
      "high": 9950,
      "low": 9700,
      "change": 0,
      "turnover": 13148980,
      "volume": 78,
      "deals": 31,
      "marketCap": 1641,
      "pe": null,
      "eps": null,
      "dividendYield": null,
      "dividendPerShare": null,
      "bookValue": null,
      "pb": null,
      "sharesOutstanding": null
    },
    {
      "symbol": "TCPLC",
      "name": "Tanzania Cigarette Plc",
      "price": 0,
      "open": 0,
      "prevClose": 0,
      "high": 0,
      "low": 0,
      "change": 0,
      "turnover": 0,
      "volume": 0,
      "deals": 0,
      "marketCap": 0,
      "pe": null,
      "eps": null,
      "dividendYield": null,
      "dividendPerShare": null,
      "bookValue": null,
      "pb": null,
      "sharesOutstanding": null
    },
    {
      "symbol": "TOL",
      "name": "Tanzania Oxygen Ltd",
      "price": 1420,
      "open": 1440,
      "prevClose": 1420,
      "high": 1450,
      "low": 1410,
      "change": 0,
      "turnover": 3974250,
      "volume": 1262,
      "deals": 43,
      "marketCap": 57108,
      "pe": null,
      "eps": null,
      "dividendYield": null,
      "dividendPerShare": null,
      "bookValue": null,
      "pb": null,
      "sharesOutstanding": null
    },
    {
      "symbol": "TTP",
      "name": "Tanzania Tea Packers Ltd",
      "price": 455,
      "open": 455,
      "prevClose": 455,
      "high": 500,
      "low": 400,
      "change": 0,
      "turnover": 263370,
      "volume": 1340,
      "deals": 26,
      "marketCap": 1462,
      "pe": null,
      "eps": null,
      "dividendYield": null,
      "dividendPerShare": null,
      "bookValue": null,
      "pb": null,
      "sharesOutstanding": null
    },
    {
      "symbol": "SWALA",
      "name": "Swala Energy Ltd",
      "price": 450,
      "open": 450,
      "prevClose": 0,
      "high": 0,
      "low": 0,
      "change": 0,
      "turnover": 0,
      "volume": 0,
      "deals": 0,
      "marketCap": 0,
      "pe": null,
      "eps": null,
      "dividendYield": null,
      "dividendPerShare": null,
      "bookValue": null,
      "pb": null,
      "sharesOutstanding": null
    },
    {
      "symbol": "USL",
      "name": "Uchumi Supermarkets Ltd",
      "price": 25,
      "open": 25,
      "prevClose": 0,
      "high": 0,
      "low": 0,
      "change": 0,
      "turnover": 0,
      "volume": 3068,
      "deals": 0,
      "marketCap": 0,
      "pe": null,
      "eps": null,
      "dividendYield": null,
      "dividendPerShare": null,
      "bookValue": null,
      "pb": null,
      "sharesOutstanding": null
    },
    {
      "symbol": "MKCB",
      "name": "Mkuki Commercial Bank Plc",
      "price": 4170,
      "open": 4230,
      "prevClose": 4170,
      "high": 4180,
      "low": 4120,
      "change": 0,
      "turnover": 2606340,
      "volume": 1935,
      "deals": 19,
      "marketCap": 8866,
      "pe": null,
      "eps": null,
      "dividendYield": null,
      "dividendPerShare": null,
      "bookValue": null,
      "pb": null,
      "sharesOutstanding": null
    },
    {
      "symbol": "MCB",
      "name": "Mwalimu Commercial Bank Plc",
      "price": 825,
      "open": 820,
      "prevClose": 825,
      "high": 900,
      "low": 800,
      "change": 0.61,
      "turnover": 3969600,
      "volume": 3899,
      "deals": 74,
      "marketCap": 590,
      "pe": null,
      "eps": null,
      "dividendYield": null,
      "dividendPerShare": null,
      "bookValue": null,
      "pb": null,
      "sharesOutstanding": null
    },
    {
      "symbol": "YETU",
      "name": "Yetu Microfinance Bank Plc",
      "price": 510,
      "open": 510,
      "prevClose": 0,
      "high": 0,
      "low": 0,
      "change": 0,
      "turnover": 0,
      "volume": 0,
      "deals": 0,
      "marketCap": 0,
      "pe": null,
      "eps": null,
      "dividendYield": null,
      "dividendPerShare": null,
      "bookValue": null,
      "pb": null,
      "sharesOutstanding": null
    },
    {
      "symbol": "MUCOBA",
      "name": "Mufindi Community Bank Plc",
      "price": 475,
      "open": 460,
      "prevClose": 475,
      "high": 495,
      "low": 455,
      "change": 3.26,
      "turnover": 306985,
      "volume": 3193,
      "deals": 13,
      "marketCap": 9607,
      "pe": null,
      "eps": null,
      "dividendYield": null,
      "dividendPerShare": null,
      "bookValue": null,
      "pb": null,
      "sharesOutstanding": null
    },
    {
      "symbol": "VODA",
      "name": "Vodacom Tanzania Plc",
      "price": 805,
      "open": 795,
      "prevClose": 805,
      "high": 815,
      "low": 800,
      "change": 1.26,
      "turnover": 44055485,
      "volume": 22333,
      "deals": 166,
      "marketCap": 26601,
      "pe": null,
      "eps": null,
      "dividendYield": null,
      "dividendPerShare": null,
      "bookValue": null,
      "pb": null,
      "sharesOutstanding": null
    },
    {
      "symbol": "AFRIPRISE",
      "name": "Afriprise Holdings Ltd",
      "price": 640,
      "open": 645,
      "prevClose": 640,
      "high": 645,
      "low": 635,
      "change": 0,
      "turnover": 18795175,
      "volume": 24583,
      "deals": 167,
      "marketCap": 19006,
      "pe": null,
      "eps": null,
      "dividendYield": null,
      "dividendPerShare": null,
      "bookValue": null,
      "pb": null,
      "sharesOutstanding": null
    },
    {
      "symbol": "JATU",
      "name": "Jatu Plc",
      "price": 265,
      "open": 265,
      "prevClose": 0,
      "high": 0,
      "low": 0,
      "change": 0,
      "turnover": 0,
      "volume": 0,
      "deals": 0,
      "marketCap": 0,
      "pe": null,
      "eps": null,
      "dividendYield": null,
      "dividendPerShare": null,
      "bookValue": null,
      "pb": null,
      "sharesOutstanding": null
    },
    {
      "symbol": "TCC",
      "name": "Tanzania Cement Company Plc",
      "price": 12490,
      "open": 12520,
      "prevClose": 12490,
      "high": 12500,
      "low": 12400,
      "change": 0,
      "turnover": 12366400,
      "volume": 43,
      "deals": 22,
      "marketCap": 482,
      "pe": null,
      "eps": null,
      "dividendYield": null,
      "dividendPerShare": null,
      "bookValue": null,
      "pb": null,
      "sharesOutstanding": null
    },
    {
      "symbol": "TPCC",
      "name": "Tanzania Portland Cement Plc",
      "price": 6260,
      "open": 6260,
      "prevClose": 6260,
      "high": 6300,
      "low": 6150,
      "change": 0,
      "turnover": 14172940,
      "volume": 2671,
      "deals": 35,
      "marketCap": 10915,
      "pe": null,
      "eps": null,
      "dividendYield": null,
      "dividendPerShare": null,
      "bookValue": null,
      "pb": null,
      "sharesOutstanding": null
    }
  ]
}